nmmn/__init__.py
nmmn/astro.py
nmmn/bayes.py
nmmn/dsp.py
nmmn/fermi.py
nmmn/finance.py
nmmn/grmhd.py
nmmn/lsd.py
nmmn/misc.py
nmmn/ml.py
nmmn/peakdetect.py
nmmn/plots.py
nmmn/sed.py
nmmn/stats.py
nmmn-1.3.6.dist-info/LICENSE
nmmn-1.3.6.dist-info/METADATA
nmmn-1.3.6.dist-info/WHEEL
nmmn-1.3.6.dist-info/top_level.txt
nmmn-1.3.6.dist-info/RECORD
