Metadata-Version: 2.1
Name: nmmn
Version: 1.3.6
Summary: Miscellaneous methods for data science and astronomy
Home-page: https://github.com/rsnemmen/nmmn
Download-URL: https://github.com/rsnemmen/nmmn/archive/1.3.6.tar.gz
Author: Rodrigo Nemmen
Author-email: rodrigo.nemmen@iag.usp.br
License: MIT License
Keywords: science,statistics,signal-processing,numerical-methods,astronomy,numerical-simulations,astrophysics,mhd,grmhd
License-File: LICENSE
